{
    "chain_name": "orxono",
    "coingecko": "orxono",
    "api": [
        {"provider": "orxono", "address": "http://localhost:1317"}
    ],
    "rpc": [
        {"provider": "orxono", "address": "http://localhost:26657"}
    ],
    "sdk_version": "0.46.1",
    "coin_type": "118",
    "min_tx_fee": "800",
    "addr_prefix": "orxono",
    "logo": "/logos/osmosis.jpg",
    "theme_color": "#812cd6",
    "assets": [{
        "base": "orxo",
        "symbol": "ORXO",
        "exponent": "1",
        "coingecko_id": "orxo", 
        "logo": "/logos/osmosis.jpg"
    },{
        "base": "aoxc",
        "symbol": "AOXC",
        "exponent": "1",
        "coingecko_id": "aoxc", 
        "logo": "/logos/osmosis.jpg"
    }]
}
